MANIFEST.in
README.md
setup.py
north_manager/__init__.py
north_manager/__version__.py
north_manager/api.py
north_manager/cli.py
north_manager/config.ini
north_manager/north_manager.py
north_manager.egg-info/PKG-INFO
north_manager.egg-info/SOURCES.txt
north_manager.egg-info/dependency_links.txt
north_manager.egg-info/entry_points.txt
north_manager.egg-info/requires.txt
north_manager.egg-info/top_level.txt
north_manager/gui/__init__.py
north_manager/gui/main.py
north_manager/gui/mainWindow.qml
north_manager/gui/models.py
north_manager/gui/object.py
north_manager/tasks/__init__.py
north_manager/tasks/firmware.py
north_manager/tasks/root.py