Metadata-Version: 2.1
Name: north-manager
Version: 0.0.10
Summary: Command line and GUI utility to manage North Robotics devices
Home-page: https://gitlab.com/north-robotics/north_manager
Author: Sean Clark
Author-email: sclark@northrobotics.com
License: MIT
Platform: UNKNOWN
Requires-Python: >=3.6.0
